alacrity/__init__.py
alacrity/core.py
alacrity/lib.py
alacrity/version.py
alacrity/starters/APACHE2_LICENSE
alacrity/starters/GPL_LICENSE
alacrity/starters/MANIFEST.in
alacrity/starters/MIT_LICENSE
alacrity/starters/Makefile
alacrity/starters/README.rst
alacrity/starters/__init__.py
alacrity/starters/gitignore.txt
alacrity/starters/requirements.txt
alacrity/starters/setup.py
alacrity/tests/__init__.py
alacrity/tests/test_lib.py
alacrity/tests/starters/__init__.py
alacrity/tests/starters/setup.py
alacrity-1.4.1.dist-info/LICENSE
alacrity-1.4.1.dist-info/METADATA
alacrity-1.4.1.dist-info/WHEEL
alacrity-1.4.1.dist-info/entry_points.txt
alacrity-1.4.1.dist-info/top_level.txt
alacrity-1.4.1.dist-info/RECORD
