Metadata-Version: 2.1
Name: alacrity
Version: 1.4.1
Summary: Quickstart your Python development with CLI package templating
Home-page: UNKNOWN
Author: Vishnuvardhan Kumar
Author-email: vishnukumar1997@gmail.com
License: UNKNOWN
Platform: UNKNOWN
Classifier: Programming Language :: Python :: 3.5
Classifier: Programming Language :: Python :: 3.6
Classifier: Programming Language :: Python :: 3.7
Classifier: Programming Language :: Python :: 3.8
Classifier: License :: OSI Approved :: MIT License
Classifier: Operating System :: OS Independent
Requires-Dist: clint
